wyoming/__init__.py
wyoming/asr.py
wyoming/asr_fallback_server.py
wyoming/audio.py
wyoming/client.py
wyoming/error.py
wyoming/event.py
wyoming/handle.py
wyoming/info.py
wyoming/intent.py
wyoming/mic.py
wyoming/ping.py
wyoming/pipeline.py
wyoming/py.typed
wyoming/pyaudioop.py
wyoming/satellite.py
wyoming/server.py
wyoming/snd.py
wyoming/timer.py
wyoming/tts.py
wyoming/vad.py
wyoming/version.py
wyoming/wake.py
wyoming/zeroconf.py
wyoming/http/__init__.py
wyoming/http/asr_server.py
wyoming/http/intent_server.py
wyoming/http/shared.py
wyoming/http/tts_server.py
wyoming/http/wake_server.py
wyoming/http/conf/asr.yaml
wyoming/http/conf/intent.yaml
wyoming/http/conf/tts.yaml
wyoming/http/conf/wake.yaml
wyoming/util/__init__.py
wyoming/util/dataclasses_json.py
wyoming-1.7.1.dist-info/licenses/LICENSE.md
wyoming-1.7.1.dist-info/METADATA
wyoming-1.7.1.dist-info/WHEEL
wyoming-1.7.1.dist-info/top_level.txt
wyoming-1.7.1.dist-info/RECORD
