Metadata-Version: 2.4
Name: wyoming
Version: 1.7.1
Summary: Peer-to-peer protocol for voice assistants
Author-email: Michael Hansen <mike@rhasspy.org>
License: MIT
Project-URL: Homepage, http://github.com/OHF-voice/wyoming
Keywords: voice,assistant,protocol
Classifier: Development Status :: 3 - Alpha
Classifier: Intended Audience :: Developers
Classifier: Topic :: Text Processing :: Linguistic
Classifier: Programming Language :: Python :: 3.8
Classifier: Programming Language :: Python :: 3.9
Classifier: Programming Language :: Python :: 3.10
Classifier: Programming Language :: Python :: 3.11
Classifier: Programming Language :: Python :: 3.12
Classifier: Programming Language :: Python :: 3.13
Requires-Python: >=3.8
License-File: LICENSE.md
Provides-Extra: dev
Requires-Dist: black==22.12.0; extra == "dev"
Requires-Dist: flake8==7.0.0; extra == "dev"
Requires-Dist: isort==5.11.3; extra == "dev"
Requires-Dist: mypy==0.991; extra == "dev"
Requires-Dist: pylint==2.15.9; extra == "dev"
Requires-Dist: pytest==7.4.4; extra == "dev"
Requires-Dist: pytest-asyncio==0.23.3; extra == "dev"
Requires-Dist: build==1.2.2.post1; extra == "dev"
Provides-Extra: zeroconf
Requires-Dist: zeroconf==0.88.0; extra == "zeroconf"
Provides-Extra: http
Requires-Dist: Flask[async]==3.0.2; extra == "http"
Requires-Dist: swagger-ui-py==23.9.23; extra == "http"
Dynamic: license-file
